deeptan/__init__.py
deeptan/cli/__init__.py
deeptan/cli/deeptan_fit.py
deeptan/cli/deeptan_litdata.py
deeptan/cli/deeptan_perturb.py
deeptan/cli/deeptan_pkl2h5.py
deeptan/cli/deeptan_predict.py
deeptan/cli/hello.py
deeptan/cli/print_sc_h5.py
deeptan/constants/__init__.py
deeptan/constants/art.py
deeptan/constants/default.py
deeptan/constants/dict_key.py
deeptan/constants/fname.py
deeptan/constants/hparam_candidates.py
deeptan/graph/__init__.py
deeptan/graph/model.py
deeptan/graph/modules.py
deeptan/graph/recon.py
deeptan/utils/__init__.py
deeptan/utils/data.py
deeptan/utils/metrics.py
deeptan/utils/peaks.py
deeptan/utils/uni.py
deeptan-0.1.5.dist-info/METADATA
deeptan-0.1.5.dist-info/WHEEL
deeptan-0.1.5.dist-info/entry_points.txt
deeptan-0.1.5.dist-info/licenses/LICENSE
deeptan-0.1.5.dist-info/RECORD
