Metadata-Version: 2.4
Name: deeptan
Version: 0.1.5
Summary: DeepTAN: A multi-task framework designed to infer multi-omics trait-associated networks and reconstruct phenotype-specific omics states from mosaic data input.
Project-URL: Homepage, https://github.com/cma2015/DeepTAN
Author-email: Chenhua Wu <chanhuawu@outlook.com>
Maintainer-email: Chenhua Wu <chanhuawu@outlook.com>
License:                     GNU GENERAL PUBLIC LICENSE
License-File: LICENSE
Keywords: bioinformatics,deep learning,pytorch
Classifier: Development Status :: 2 - Pre-Alpha
Classifier: Environment :: Console
Classifier: Environment :: GPU :: NVIDIA CUDA :: 12
Classifier: Intended Audience :: Science/Research
Classifier: License :: OSI Approved :: GNU General Public License v3 (GPLv3)
Classifier: Natural Language :: Chinese (Simplified)
Classifier: Natural Language :: English
Classifier: Operating System :: POSIX :: Linux
Classifier: Programming Language :: Python :: 3.10
Classifier: Programming Language :: Python :: 3.11
Classifier: Programming Language :: Python :: 3.12
Classifier: Topic :: Scientific/Engineering :: Bio-Informatics
Requires-Python: <3.13,>=3.10
Requires-Dist: jupyterlab-lsp>=5.1.1
Requires-Dist: jupyterlab>=4.4.3
Requires-Dist: leidenalg>=0.10.2
Requires-Dist: lightning>=2.5.1.post0
Requires-Dist: litdata>=0.2.49
Requires-Dist: mosaicml-streaming>=0.12.0
Requires-Dist: numpy>=2.1.2
Requires-Dist: optuna-dashboard>=0.18.0
Requires-Dist: optuna>=4.3.0
Requires-Dist: pacmap>=0.8.0
Requires-Dist: polars>=1.30.0
Requires-Dist: pyarrow>=19.0.0
Requires-Dist: pyg-lib
Requires-Dist: scanpy>=1.11.2
Requires-Dist: scib-metrics>=0.5.4
Requires-Dist: scikit-learn>=1.6.1
Requires-Dist: scikit-misc>=0.5.1
Requires-Dist: scipy>=1.15.1
Requires-Dist: setuptools>=78.1.1
Requires-Dist: tensorboard>=2.18.0
Requires-Dist: torch-cluster
Requires-Dist: torch-geometric>=2.6.1
Requires-Dist: torch-scatter
Requires-Dist: torch-sparse
Requires-Dist: torch-spline-conv
Requires-Dist: torch==2.7.0
Requires-Dist: torchaudio==2.7.0
Requires-Dist: torchmetrics>=1.7.1
Requires-Dist: torchvision==0.22.0
Requires-Dist: tqdm>=4.67.1
Requires-Dist: zstd>=1.5.7.0
